aiobreaker/__init__.py
aiobreaker/circuitbreaker.py
aiobreaker/listener.py
aiobreaker/state.py
aiobreaker/version.py
aiobreaker/storage/__init__.py
aiobreaker/storage/base.py
aiobreaker/storage/memory.py
aiobreaker/storage/redis.py
test/__init__.py
test/conftest.py
test/test_circuit.py
test/test_circuit_async.py
test/test_configuration.py
test/test_configuration_async.py
test/test_listener.py
test/tests-old.py
test/util.py
aiobreaker-1.1.0.dist-info/METADATA
aiobreaker-1.1.0.dist-info/WHEEL
aiobreaker-1.1.0.dist-info/top_level.txt
aiobreaker-1.1.0.dist-info/RECORD
