Metadata-Version: 2.1
Name: aiobreaker
Version: 1.1.0
Summary: Python implementation of the Circuit Breaker pattern.
Home-page: https://github.com/arlyon/aiobreaker
Author: Alexander Lyon
Author-email: arlyon@me.com
License: BSD
Platform: UNKNOWN
Classifier: Intended Audience :: Developers
Classifier: License :: OSI Approved :: BSD License
Classifier: Programming Language :: Python
Classifier: Programming Language :: Python :: 3.5
Classifier: Topic :: Software Development :: Libraries
Requires-Python: >=3.5
Provides-Extra: docs
Requires-Dist: sphinx ; extra == 'docs'
Requires-Dist: sphinx-rtd-theme ; extra == 'docs'
Requires-Dist: sphinx-autobuild ; extra == 'docs'
Requires-Dist: sphinx-autodoc-typehints ; extra == 'docs'
Provides-Extra: redis
Requires-Dist: redis ; extra == 'redis'
Provides-Extra: test
Requires-Dist: fakeredis ; extra == 'test'
Requires-Dist: pytest (>4) ; extra == 'test'
Requires-Dist: pytest-asyncio ; extra == 'test'
Requires-Dist: mypy ; extra == 'test'
Requires-Dist: pylint ; extra == 'test'
Requires-Dist: safety ; extra == 'test'
Requires-Dist: bandit ; extra == 'test'
Requires-Dist: codecov ; extra == 'test'
Requires-Dist: pytest-cov ; extra == 'test'
